centreon_report_to_pdf/BuildPDF.py
centreon_report_to_pdf/CentreonData.py
centreon_report_to_pdf/GlobalVars.py
centreon_report_to_pdf/SMTP.py
centreon_report_to_pdf/Settings.py
centreon_report_to_pdf/centreon_report_to_pdf.py
centreon_report_to_pdf/config_example.ini
centreon_report_to_pdf/email_body.txt
centreon_report_to_pdf/requirements.txt
centreon_report_to_pdf-1.5.4.dist-info/METADATA
centreon_report_to_pdf-1.5.4.dist-info/WHEEL
centreon_report_to_pdf-1.5.4.dist-info/top_level.txt
centreon_report_to_pdf-1.5.4.dist-info/RECORD
