Metadata-Version: 2.1
Name: centreon-report-to-pdf
Version: 1.5.4
Summary: Generate a PDF from Centreon Dashboard and optional sent it by email
Home-page: https://github.com/vhsantos/centreon_report_to_pdf
Download-URL: https://github.com/vhsantos/centreon_report_to_pdf/archive/v1.5.4.tar.gz
Author: Victor Hugo dos Santos
Author-email: listas.vhs@gmail.com
Keywords: centreon report pdf email dashboard
Classifier: Programming Language :: Python :: 3.5
Classifier: Topic :: System :: Monitoring
Classifier: Development Status :: 6 - Mature
Classifier: Intended Audience :: System Administrators
Classifier: Operating System :: OS Independent
Classifier: Environment :: Console
Requires-Dist: reportlab (>=3.5)
Requires-Dist: pandas (>=1.0)
Requires-Dist: requests (>=2.23)
Requires-Dist: pytz (>=2022.1)
